config/dim_names_map.yaml
config/meta_attributes.yaml
config/meta_coordinates.yaml
config/sample_app.yaml
config/sample_specs.yaml
eviz/__about__.py
eviz/__init__.py
eviz/lib/__init__.py
eviz/lib/const.py
eviz/lib/eviz_base.py
eviz/lib/iviz_base.py
eviz/lib/utils.py
eviz/lib/xarray_utils.py
eviz/lib/data/__init__.py
eviz/lib/data/airnow_reader.py
eviz/lib/data/base_reader.py
eviz/lib/data/csv_reader.py
eviz/lib/data/data_selector.py
eviz/lib/data/data_source.py
eviz/lib/data/data_utils.py
eviz/lib/data/hdf4_reader.py
eviz/lib/data/hdf5_reader.py
eviz/lib/data/landsat_reader.py
eviz/lib/data/lis_reader.py
eviz/lib/data/netcdf4_reader.py
eviz/lib/data/netcdf_reader.py
eviz/lib/data/omi_reader.py
eviz/lib/data/processor.py
eviz/lib/data/reader.py
eviz/lib/data/tabular_reader.py
eviz/lib/data/wrf_reader.py
eviz/lib/eviz/__init__.py
eviz/lib/eviz/config.py
eviz/lib/eviz/figure.py
eviz/lib/eviz/operations.py
eviz/lib/eviz/overlays.py
eviz/lib/eviz/plot_utils.py
eviz/lib/eviz/plottable.py
eviz/lib/eviz/plotter.py
eviz/lib/eviz/geos/__init__.py
eviz/lib/eviz/geos/geos_history.py
eviz/lib/iviz/__init__.py
eviz/lib/iviz/base_params.py
eviz/lib/iviz/config.py
eviz/lib/iviz/dash_utils.py
eviz/lib/iviz/dataframe_params.py
eviz/lib/iviz/notyf.py
eviz/lib/iviz/params.py
eviz/lib/iviz/params_util.py
eviz/lib/iviz/time_average.py
eviz/models/__init__.py
eviz/models/root.py
eviz/models/root_factory.py
eviz/models/esm/__init__.py
eviz/models/esm/generic.py
eviz/models/esm/geos.py
eviz/models/esm/lis.py
eviz/models/esm/nuwrf.py
eviz/models/esm/wrf.py
eviz/models/iviz/__init__.py
eviz/models/iviz/airnow_dashboard.py
eviz/models/iviz/base_dashboard.py
eviz/models/iviz/cf_dashboard.py
eviz/models/iviz/lis_dashboard.py
eviz/models/iviz/multi_file.py
eviz/models/iviz/root_dashboard.py
eviz/models/iviz/tabular_dashboard.py
eviz/models/iviz/wrf_dashboard.py
eviz/models/obs/__init__.py
eviz/models/obs/inventory/__init__.py
eviz/models/obs/inventory/airnow.py
eviz-0.5.0.dist-info/AUTHORS.txt
eviz-0.5.0.dist-info/LICENSE
eviz-0.5.0.dist-info/METADATA
eviz-0.5.0.dist-info/WHEEL
eviz-0.5.0.dist-info/top_level.txt
eviz-0.5.0.dist-info/RECORD
