Metadata-Version: 2.1
Name: eviz
Version: 0.5.0
Summary: An easy to use visualization framework for Earth system models
Author: Deon Kouatchou-Ngongang, Aarav Khanna
Author-email: Carlos Cruz <carlos.a.cruz@nasa.gov>, Vanessa Valenti <vanessa.l.valenti@nasa.gov>, Deepthi Raghunandan <deepthi.raghunandan@nasa.gov>, Jules Kouatchou <jules.r.kouatchou@nasa.gov>
License: 
Project-URL: Repository, https://git.mysmce.com/astg/visualization/eviz
Project-URL: Documentation, https://astg.pages.smce.nasa.gov/visualization/eviz/
Classifier: Programming Language :: Python :: 3
Classifier: Programming Language :: Python :: 3.10
Classifier: License :: OSI Approved :: Apache Software License
Classifier: Operating System :: OS Independent
Requires-Python: >=3.10
License-File: LICENSE
License-File: AUTHORS.txt
Requires-Dist: xesmf >=0.7.1
Requires-Dist: xarray >=2023.12.0
Requires-Dist: hdf5 >=1.14.3
Requires-Dist: sparse >=0.14.0
Requires-Dist: matplotlib-base >=3.8.2
Requires-Dist: cartopy >=0.22
Requires-Dist: geos >=3.12.1
Requires-Dist: proj >=9.3.1
Requires-Dist: pyyaml >=6.0.1
Requires-Dist: yaml >=0.2.5
Requires-Dist: dask >=2023.12.1
Requires-Dist: cftime >=1.6.3
Requires-Dist: netcdf4 >=1.6.5
Requires-Dist: holoviews >=1.16
Requires-Dist: datashader >=0.16.0
Requires-Dist: hvplot >=0.9.1
Requires-Dist: geoviews-core >=1.11.0
Requires-Dist: pyhdf >=0.11.3
Requires-Dist: h5py >=3.10.0
Requires-Dist: selenium >=4.1.0
Requires-Dist: pydap >=3.4.0
Requires-Dist: geopandas >=0.14.2
Requires-Dist: streamlit >=1.30.0
Requires-Dist: seaborn >=0.13.1
Requires-Dist: pytest >=7.4.4
Requires-Dist: ipykernel >=6.28.0
